watson/__init__.py
watson/__main__.py
watson/autocompletion.py
watson/cli.py
watson/config.py
watson/frames.py
watson/fullmoon.py
watson/utils.py
watson/version.py
watson/watson.py
td_watson-2.1.0.dist-info/LICENSE
td_watson-2.1.0.dist-info/METADATA
td_watson-2.1.0.dist-info/WHEEL
td_watson-2.1.0.dist-info/entry_points.txt
td_watson-2.1.0.dist-info/top_level.txt
td_watson-2.1.0.dist-info/RECORD
