Metadata-Version: 2.1
Name: td-watson
Version: 2.1.0
Summary: A wonderful CLI to track your time!
Home-page: https://github.com/TailorDev/Watson
Author: TailorDev
Author-email: contact@tailordev.fr
License: MIT
Keywords: watson time-tracking time tracking monitoring report
Classifier: Development Status :: 5 - Production/Stable
Classifier: Intended Audience :: Customer Service
Classifier: Intended Audience :: End Users/Desktop
Classifier: Intended Audience :: Information Technology
Classifier: Intended Audience :: Science/Research
Classifier: Intended Audience :: Other Audience
Classifier: License :: OSI Approved :: MIT License
Classifier: Environment :: Console
Classifier: Operating System :: MacOS
Classifier: Operating System :: Microsoft :: Windows
Classifier: Operating System :: POSIX
Classifier: Programming Language :: Python :: 3
Classifier: Programming Language :: Python :: 3.5
Classifier: Programming Language :: Python :: 3.6
Classifier: Programming Language :: Python :: 3.7
Classifier: Programming Language :: Python :: 3.8
Classifier: Programming Language :: Python :: 3.9
Classifier: Topic :: Office/Business
Classifier: Topic :: Utilities
Requires-Python: >=3.6
License-File: LICENSE
Requires-Dist: requests
Requires-Dist: arrow (>=1.0.0)
Requires-Dist: click (>=8.0)
Requires-Dist: click-didyoumean
Requires-Dist: colorama ; sys_platform == "win32"
